{
	"candidates": [
		{
			"name" : "Fuuko Izumo",
			"source" : "Undead Unluck",
			"selected": false,
			"img" : "/img/762.jpg"
		},
		{
			"name" : "Andy",
			"source" : "Undead Unluck",
			"selected": false,
			"img" : "/img/763.jpg"
		},
		{
			"name" : "Maomao",
			"source" : "Kusuriya no Hitorigoto",
			"selected": false,
			"img" : "/img/764.jpg"
		},
		{
			"name" : "Gesicht",
			"source" : "Pluto",
			"selected": false,
			"img" : "/img/765.jpg"
		},
		{
			"name" : "Atom",
			"source" : "Pluto",
			"selected": false,
			"img" : "/img/766.jpg"
		},
		{
			"name" : "Shary Shadow Assassin",
			"source" : "Seiken Gakuin no Makentsukai",
			"selected": false,
			"img" : "/img/767.jpg"
		},
		{
			"name" : "Pram Schneider",
			"source" : "Kikansha no Mahou wa Tokubetsu desu",
			"selected": false,
			"img" : "/img/768.jpg"
		},
		{
			"name" : "Azest Kingscrown",
			"source" : "Kikansha no Mahou wa Tokubetsu desu",
			"selected": false,
			"img" : "/img/769.jpg"
		},
		{
			"name" : "Romantica Eru",
			"source" : "Kikansha no Mahou wa Tokubetsu desu",
			"selected": false,
			"img" : "/img/770.jpg"
		},
		{
			"name" : "Terakomari Gandesblood",
			"source" : "Hikikomari Kyuuketsuki no Monmon",
			"selected": false,
			"img" : "/img/771.jpg"
		},
		{
			"name" : "Villhaze",
			"source" : "Hikikomari Kyuuketsuki no Monmon",
			"selected": false,
			"img" : "/img/772.jpg"
		},
		{
			"name" : "Mia Luna Tearmoon",
			"source" : "Tearmoon Teikoku Monogatari: Dantoudai kara Hajimaru, Hime no Tensei Gyakuten Story",
			"selected": false,
			"img" : "/img/773.jpg"
		},
		{
			"name" : "Jess Yesma",
			"source" : "Buta no Liver wa Kanetsu Shiro",
			"selected": false,
			"img" : "/img/774.jpg"
		},
		{
			"name" : "Pig",
			"source" : "Buta no Liver wa Kanetsu Shiro",
			"selected": false,
			"img" : "/img/775.jpg"
		},
		{
			"name" : "Rossi",
			"source" : "Buta no Liver wa Kanetsu Shiro",
			"selected": false,
			"img" : "/img/776.jpg"
		},
		{
			"name" : "Fairy Queen",
			"source" : "Toaru Ossan no VRMMO Katsudouki",
			"selected": false,
			"img" : "/img/777.jpg"
		},
		{
			"name" : "Konoha Akisato",
			"source" : "16bit Sensation: Another Layer",
			"selected": false,
			"img" : "/img/778.jpg"
		},
		{
			"name" : "Totomaru Isshiki",
			"source" : "Kamonohashi Ron no Kindan Suiri",
			"selected": false,
			"img" : "/img/779.jpg"
		},
		{
			"name" : "Ron Kamonohashi",
			"source" : "Kamonohashi Ron no Kindan Suiri",
			"selected": false,
			"img" : "/img/780.jpg"
		},
		{
			"name" : "Kanata Katagiri",
			"source" : "MF Ghost",
			"selected": false,
			"img" : "/img/781.jpg"
		},
		{
			"name" : "Haruka Asahina",
			"source" : "Overtake!",
			"selected": false,
			"img" : "/img/782.jpg"
		},
		{
			"name" : "Koutarou Komaki",
			"source" : "Overtake!",
			"selected": false,
			"img" : "/img/783.jpg"
		},
		{
			"name" : "Toshiki Tokumaru",
			"source" : "Overtake!",
			"selected": false,
			"img" : "/img/784.jpg"
		},
		{
			"name" : "Youko Sonoyama",
			"source" : "Migi to Dali",
			"selected": false,
			"img" : "/img/785.jpg"
		},
		{
			"name" : "Russian Foreigner",
			"source" : "Under Ninja",
			"selected": false,
			"img" : "/img/786.jpg"
		},
		{
			"name" : "Sein",
			"source" : "Sousou no Frieren",
			"selected": false,
			"img" : "/img/787.jpg"
		},
		{
			"name" : "Ren Saionji",
			"source" : "MF Ghost",
			"selected": false,
			"img" : "/img/788.jpg"
		},
		{
			"name" : "Frieren",
			"source" : "Sousou no Frieren",
			"selected": false,
			"img" : "/img/789.jpg"
		},
		{
			"name" : "Fern",
			"source" : "Sousou no Frieren",
			"selected": false,
			"img" : "/img/790.jpg"
		},
		{
			"name" : "Flamme",
			"source" : "Sousou no Frieren",
			"selected": false,
			"img" : "/img/791.jpg"
		},
		{
			"name" : "Himmel",
			"source" : "Sousou no Frieren",
			"selected": false,
			"img" : "/img/792.jpg"
		},
		{
			"name" : "Eisen",
			"source" : "Sousou no Frieren",
			"selected": false,
			"img" : "/img/793.jpg"
		},
		{
			"name" : "Heiter",
			"source" : "Sousou no Frieren",
			"selected": false,
			"img" : "/img/794.jpg"
		},
		{
			"name" : "Jinshi",
			"source" : "Kusuriya no Hitorigoto",
			"selected": false,
			"img" : "/img/795.jpg"
		},
		{
			"name" : "Gyokuyou",
			"source" : "Kusuriya no Hitorigoto",
			"selected": false,
			"img" : "/img/796.jpg"
		},
		{
			"name" : "Rentarou Aijou",
			"source" : "Kimi no Koto ga Daidaidaidaidaisuki na 100-nin no Kanojo",
			"selected": false,
			"img" : "/img/797.jpg"
		},
		{
			"name" : "Karane Inda",
			"source" : "Kimi no Koto ga Daidaidaidaidaisuki na 100-nin no Kanojo",
			"selected": false,
			"img" : "/img/798.jpg"
		},
		{
			"name" : "Shizuka Yoshimoto",
			"source" : "Kimi no Koto ga Daidaidaidaidaisuki na 100-nin no Kanojo",
			"selected": false,
			"img" : "/img/799.jpg"
		},
		{
			"name" : "Nano Eiai",
			"source" : "Kimi no Koto ga Daidaidaidaidaisuki na 100-nin no Kanojo",
			"selected": false,
			"img" : "/img/800.jpg"
		},
		{
			"name" : "Hakari Hanazono",
			"source" : "Kimi no Koto ga Daidaidaidaidaisuki na 100-nin no Kanojo",
			"selected": false,
			"img" : "/img/801.jpg"
		},
		{
			"name" : "Kusuri Yakuzen",
			"source" : "Kimi no Koto ga Daidaidaidaidaisuki na 100-nin no Kanojo",
			"selected": false,
			"img" : "/img/802.jpg"
		},
		{
			"name" : "Hahari Hanazono",
			"source" : "Kimi no Koto ga Daidaidaidaidaisuki na 100-nin no Kanojo",
			"selected": false,
			"img" : "/img/803.jpg"
		},
		{
			"name" : "Rae Taylor",
			"source" : "Watashi no Oshi wa Akuyaku Reijou.",
			"selected": false,
			"img" : "/img/804.jpg"
		},
		{
			"name" : "Claire François",
			"source" : "Watashi no Oshi wa Akuyaku Reijou.",
			"selected": false,
			"img" : "/img/805.jpg"
		},
		{
			"name" : "Umika Konohoshi",
			"source" : "Hoshikuzu Telepath",
			"selected": false,
			"img" : "/img/806.jpg"
		},
		{
			"name" : "Yuu Akeuchi",
			"source" : "Hoshikuzu Telepath",
			"selected": false,
			"img" : "/img/807.jpg"
		},
		{
			"name" : "FrostNova",
			"source" : "Arknights: Touin Kiro",
			"selected": false,
			"img" : "/img/808.jpg"
		}
	],
	"title": "Осень 2023"
}
